dylab/AbsorptionImaging.py
dylab/Camera.py
dylab/DyTransition.py
dylab/Fitting.py
dylab/FittingFunction.py
dylab/TransitionClass.py
dylab/__init__.py
dylab-0.0.2.dist-info/LICENSE
dylab-0.0.2.dist-info/METADATA
dylab-0.0.2.dist-info/WHEEL
dylab-0.0.2.dist-info/top_level.txt
dylab-0.0.2.dist-info/RECORD
